{
  "version": 2,
  "settings": {
    "layout": {
      "wideSize": "114rem",
      "contentSize": "1280px"
    },
    "border": {
      "color": false,
      "radius": true,
      "style": false,
      "width": false
    },
    "color": {
      "background": true,
      "custom": true,
      "customDuotone": true,
      "customGradient": true,
      "link": false,
      "duotone": [
        {
          "name":  "Dark grayscale" ,
          "colors": [ "#000000", "#7f7f7f" ],
          "slug": "dark-grayscale"
        },
        {
          "name":  "Grayscale" ,
          "colors": [ "#000000", "#ffffff" ],
          "slug": "grayscale"
        },
        {
          "name":  "Purple and yellow" ,
          "colors": [ "#8c00b7", "#fcff41" ],
          "slug": "purple-yellow"
        },
        {
          "name":  "Blue and red" ,
          "colors": [ "#000097", "#ff4747" ],
          "slug": "blue-red"
        },
        {
          "name":  "Midnight" ,
          "colors": [ "#000000", "#00a5ff" ],
          "slug": "midnight"
        },
        {
          "name":  "Magenta and yellow" ,
          "colors": [ "#c7005a", "#fff278" ],
          "slug": "magenta-yellow"
        },
        {
          "name":  "Purple and green" ,
          "colors": [ "#a60072", "#67ff66" ],
          "slug": "purple-green"
        },
        {
          "name":  "Blue and orange" ,
          "colors": [ "#1900d8", "#ffa96b" ],
          "slug": "blue-orange"
        }
      ],
      "gradients": [
        {
          "name": "Primary",
          "gradient": "linear-gradient(45deg,#3d34d2 0%, #7871fc 100%)",
          "slug": "primary-blue-gradient"
        },
        {
          "name": "Vivid cyan blue to vivid purple",
          "gradient": "linear-gradient(45deg,rgba(6,147,227,1) 0%,rgb(155,81,224) 100%)",
          "slug": "vivid-cyan-blue-to-vivid-purple"
        },
        {
          "name": "Luminous vivid amber to luminous vivid orange",
          "gradient": "linear-gradient(45deg,rgba(252,185,0,1) 0%,rgba(255,105,0,1) 100%)",
          "slug": "luminous-vivid-amber-to-luminous-vivid-orange"
        },
        {
          "name": "Luminous vivid orange to vivid red",
          "gradient": "linear-gradient(45deg,rgba(255,105,0,1) 0%,rgb(207,46,46) 100%)",
          "slug": "luminous-vivid-orange-to-vivid-red"
        },
        {
          "name": "Cool to warm spectrum",
          "gradient": "linear-gradient(45deg,rgb(74,234,220) 0%,rgb(151,120,209) 20%,rgb(207,42,186) 40%,rgb(238,44,130) 60%,rgb(251,105,98) 80%,rgb(254,248,76) 100%)",
          "slug": "cool-to-warm-spectrum"
        },
        {
          "name": "Blush light purple",
          "gradient": "linear-gradient(45deg,rgb(255,206,236) 0%,rgb(152,150,240) 100%)",
          "slug": "blush-light-purple"
        },
        {
          "name": "Blush bordeaux",
          "gradient": "linear-gradient(45deg,rgb(254,205,165) 0%,rgb(254,45,45) 50%,rgb(107,0,62) 100%)",
          "slug": "blush-bordeaux"
        },
        {
          "name": "Luminous dusk",
          "gradient": "linear-gradient(45deg,rgb(255,203,112) 0%,rgb(199,81,192) 50%,rgb(65,88,208) 100%)",
          "slug": "luminous-dusk"
        },
        {
          "name": "Electric grass",
          "gradient": "linear-gradient(45deg,rgb(202,248,128) 0%,rgb(113,206,126) 100%)",
          "slug": "electric-grass"
        }
      ],
      "palette": [
        {
          "name": "Primary",
          "slug": "primary",
          "color": "#0EA5E9"
        },
        {
          "name": "Yellow",
          "slug": "secondary",
          "color": "#FDAE56"
        },
        {
          "name": "Yellow 2 (store link)",
          "slug": "yellow-sl",
          "color": "#FFAE4C"
        },
        {
          "name": "Grey",
          "slug": "d-grey",
          "color": "#7E7975"
        },
        {
          "name": "g-bc-dark",
          "slug": "g-bc-dark",
          "color": "#4d4d4d"
        },
        {
          "name": "Dark",
          "slug": "dark",
          "color": "#1F2937"
        },
        {
          "name": "Light",
          "slug": "light",
          "color": "#F9FAFB"
        }
      ]
    },
    "spacing": {
      "blockGap": null,
      "margin": false,
      "padding": false,
      "units": [ "px", "em", "rem", "vh", "vw", "%" ]
    },
    "typography": {
      "customFontSize": false,
      "dropCap": true,
      "fontSizes": [
        {
          "name": "xs",
          "slug": "xs",
          "size": "0.75rem"
        },
        {
          "slug": "sm",
          "name": "sm",
          "size": "0.875rem"
        },
        {
          "slug": "base",
          "name": "base",
          "size": "1rem"
        },
        {
          "slug": "lg",
          "name": "lg",
          "size": "1.25rem"
        },
        {
          "slug": "2xl",
          "name": "2xl",
          "size": "1.5rem"
        },
        {
          "slug": "3xl",
          "name": "3xl",
          "size": "1.875rem"
        },
        {
          "slug": "4xl",
          "name": "4xl",
          "size": "2.25rem"
        },
        {
          "slug": "5xl",
          "name": "5xl",
          "size": "3rem"
        },
        {
          "slug": "6xl",
          "name": "6xl",
          "size": "3.75rem"
        },
        {
          "slug": "7xl",
          "name": "7xl",
          "size": "4.5rem"
        },
        {
          "slug": "8xl",
          "name": "8xl",
          "size": "6rem"
        },
        {
          "slug": "9xl",
          "name": "9xl",
          "size": "8rem"
        }
      ],
      "fontStyle": true,
      "fontWeight": true,
      "letterSpacing": true,
      "lineHeight": false,
      "textDecoration": true,
      "textTransform": true
    },
    "blocks": {
      "core/button": {
        "border": {
          "radius": true
        }
      },
      "core/pullquote": {
        "border": {
          "color": true,
          "radius": true,
          "style": true,
          "width": true
        }
      },
      "core/table": {
        "border": {
          "color": true,
          "radius": true,
          "style": true,
          "width": true
        }
      }
    }
  }
}
